{
	"scenarios": {
		"mixed": [
			"-p",
			"25",
			"-l",
			"10",
			"-c",
			"2048",
			"-m",
			"55",
			"-t",
			"64",
			"-d",
			"8",
			"-i",
			"10",
			"-b",
			"10"
		],
		"compute": [
			"-p",
			"0",
			"-l",
			"0",
			"-c",
			"32768",
			"-m",
			"100",
			"-t",
			"64",
			"-d",
			"8",
			"-i",
			"0",
			"-b",
			"0"
		],
		"message": [
			"-p",
			"75",
			"-l",
			"0",
			"-c",
			"2048",
			"-m",
			"0",
			"-t",
			"64",
			"-d",
			"8",
			"-i",
			"25",
			"-b",
			"10"
		],
		"contention": [
			"-p",
			"25",
			"-l",
			"10",
			"-c",
			"2048",
			"-m",
			"55",
			"-t",
			"64",
			"-d",
			"1",
			"-i",
			"10",
			"-b",
			"10"
		],
		"server": [
			"-p",
			"90",
			"-l",
			"5",
			"-c",
			"2048",
			"-m",
			"0",
			"-t",
			"131072",
			"-d",
			"8",
			"-i",
			"5",
			"-b",
			"10"
		]
	},
	"colors": {
		"newspeak": "#FF0000",
		"caf": "#0000FF",
    "caf-head": "#00FF00",
		"pony": "#000000"
	},
	"versions": {
		"newspeak": "0.7.0",
		"caf": "0.17.5",
    "caf-head": "0.18",
		"pony": "0.34.1"
	}
}
